Metadata-Version: 2.1
Name: django-mp-history
Version: 1.1.0
Summary: Django history app
Home-page: https://github.com/pmaigutyak/mp-history
Author: Paul Maigutyak
Author-email: pmaigutyak@gmail.com
License: MIT
Download-URL: https://github.com/pmaigutyak/mp-history/archive/1.1.0.tar.gz
Platform: UNKNOWN
